Metadata-Version: 1.0
Name: NKPy
Version: 0.1.26
Summary: Nanhe Korean Python
Home-page: https://github.com/NKPy/NKPy
Author: Helloyunho, Func, Preta 「 プレタ 」, BGM
Author-email: yunho050840@gmail.com
License: MIT
Platform: UNKNOWN
